Workbook

Sheet Introduction
A1: Introduction

Sheet Assumptions
A1: Assumptions
A11: Items | C11: Growth Rate
A13: Revenues | C13: 0.03
A14: Cost of Sales | C14: 0.02
A15: Demand Creation | C15: 0.05 | D15: (marketing, endorsements, advertising.)
A16: Operating Overhead Expense | C16: 0.01
A17: Tax rate | C17: 0.15

Sheet Budgeted Figures
A1: Budgeted Figures
A5: Line Item | C5: FY2024 Actual | D5: FY 2025 Budgeted
A6: Revenues | C6: 51362 | D6: =C6*(1+Assumptions!C13) -> 52902.86
A7: Cost of Sales | C7: 28475 | D7: =-C7*(1+Assumptions!C14) -> -29044.5
A8: Gross Profit | C8: 22887 | D8: =D6+D7 -> 23858.36
A9: Demand Creation Expense | C9: 4285 | D9: =-C9*(1+Assumptions!C15) -> -4499.25
A10: Operating Overhead Expense | C10: 12291 | D10: =-C10*(1+Assumptions!C16) -> -12413.91
A11: Total SG&A | C11: 16576 | D11: =D9+D10 -> -16913.16
A12: Income Before Tax | C12: 6700 | D12: =D8+D11 -> 6945.2
A13: Income Tax Expense | C13: 1000 | D13: =-D12*Assumptions!C17 -> -1041.78
A14: Net Income | C14: 5700 | D14: =D12+D13 -> 5903.42

Sheet Actual Vs Budgeted
A1: Actual Vs Budgeted
A5: Line Item | C5: FY 2025 Budgeted | D5: FY 2025 Actual | E5: Variance | F5: Variance % | G5: U/F
A6: Revenues | C6: ='Budgeted Figures'!D6 -> 52902.86 | D6: 46309 | E6: =D6-C6 -> -6593.86 | F6: =(D6-C6)/C6 -> -0.1246409 | G6: U
A7: Cost of Sales | C7: ='Budgeted Figures'!D7 -> -29044.5 | D7: -26519 | E7: =D7-C7 -> 2525.5 | F7: =-(D7-C7)/C7 -> 0.086952779 | G7: F
A8: Gross Profit | C8: ='Budgeted Figures'!D8 -> 23858.36 | D8: =D6+D7 -> 19790 | E8: =D8-C8 -> -4068.36 | F8: =(D8-C8)/C8 -> -0.17052136 | G8: U
A9: Demand Creation Expense | C9: ='Budgeted Figures'!D9 -> -4499.25 | D9: -4689 | E9: =D9-C9 -> -189.75 | F9: =-(D9-C9)/C9 -> -0.042173696 | G9: F
A10: Operating Overhead Expense | C10: ='Budgeted Figures'!D10 -> -12413.91 | D10: -11399 | E10: =D10-C10 -> 1014.91 | F10: =-(D10-C10)/C10 -> 0.081755869 | G10: F
A11: Total SG&A | C11: ='Budgeted Figures'!D11 -> -16913.16 | D11: =D9+D10 -> -16088 | E11: =D11-C11 -> 825.16 | F11: =-(D11-C11)/C11 -> 0.048788044 | G11: F
A12: Income Before Tax | C12: ='Budgeted Figures'!D12 -> 6945.2 | D12: =D8+D11+107+76 -> 3885 | E12: =D12-C12 -> -3060.2 | F12: =(D12-C12)/C12 -> -0.44062086 | G12: U
A13: Income Tax Expense | C13: ='Budgeted Figures'!D13 -> -1041.78 | D13: -666 | E13: =D13-C13 -> 375.78 | F13: =-(D13-C13)/C13 -> 0.36070955 | G13: F
A14: Net Income | C14: ='Budgeted Figures'!D14 -> 5903.42 | D14: =D12+D13 -> 3219 | E14: =D14-C14 -> -2684.42 | F14: =(D14-C14)/C14 -> -0.45472286 | G14: U

Sheet Expalination
A1: Expalination for Variances
